airtable/__init__.py
airtable/__version__.py
airtable/airtable.py
airtable/auth.py
airtable/params.py
airtable_python_wrapper-0.15.3.dist-info/LICENSE
airtable_python_wrapper-0.15.3.dist-info/METADATA
airtable_python_wrapper-0.15.3.dist-info/WHEEL
airtable_python_wrapper-0.15.3.dist-info/top_level.txt
airtable_python_wrapper-0.15.3.dist-info/RECORD
