Metadata-Version: 2.1
Name: airtable-python-wrapper
Version: 0.15.3
Summary: Python API Wrapper for the Airtable API
Home-page: https://github.com/gtalarico/airtable-python-wrapper
Author: Gui Talarico
Author-email: gtalarico.dev@gmail.com
License: The MIT License (MIT)
Keywords: airtable,api
Platform: UNKNOWN
Classifier: Development Status :: 4 - Beta
Classifier: Environment :: Console
Classifier: Intended Audience :: Developers
Classifier: Programming Language :: Python
Classifier: Topic :: Software Development
Classifier: Programming Language :: Python
Classifier: Programming Language :: Python :: 3.5
Classifier: Programming Language :: Python :: 3.6
Classifier: Programming Language :: Python :: 3.7
Classifier: Programming Language :: Python :: 3.8
Classifier: Programming Language :: Python :: Implementation :: CPython
Requires-Python: !=2.7.*, !=3.0.*, !=3.1.*, !=3.2.*, !=3.3.*, !=3.4.*
